jupyter_slack/__init__.py
jupyter_slack/jupyter_slack.py
jupyter_slack-2.1.4.dist-info/LICENSE.txt
jupyter_slack-2.1.4.dist-info/METADATA
jupyter_slack-2.1.4.dist-info/WHEEL
jupyter_slack-2.1.4.dist-info/top_level.txt
jupyter_slack-2.1.4.dist-info/RECORD
