Metadata-Version: 2.1
Name: jupyter-slack
Version: 2.1.4
Summary: A magic command for notifying the status of code completion in jupyter notebooks via slack
Home-page: https://github.com/keitakurita/jupyter-slack-notify
Author: keitakurita
Author-email: keita.kurita@gmail.com
License: MIT
Platform: UNKNOWN
Classifier: Programming Language :: Python :: 3.5
Classifier: Programming Language :: Python :: 3.6
Classifier: Programming Language :: Python :: 3.7
Requires-Dist: requests
Requires-Dist: ipython
Requires-Dist: jupyter
